{"name":"Registro de un usuario existente","id":"validación-de-registro-con-usuario-existente;registro-de-un-usuario-existente","scenarioId":"registrar_usuario_existente:Registro de un usuario existente","methodName":"Registro de un usuario existente","testSteps":[{"number":1,"description":"Given que el usuario se encuentra en la pagina de inicio de Automation Exercise","duration":5898,"startTime":"2025-07-01T20:08:46.541882-05:00[America/Bogota]","result":"SUCCESS","precondition":false,"level":0,"children":[{"number":2,"description":"Usuario opens the Buscar producto interface","duration":5417,"startTime":"2025-07-01T20:08:47.013024300-05:00[America/Bogota]","result":"SUCCESS","precondition":false,"level":1}]},{"number":3,"description":"And la pagina de inicio es visible correctamente","duration":256,"startTime":"2025-07-01T20:08:52.441021500-05:00[America/Bogota]","result":"SUCCESS","precondition":false,"level":0,"children":[{"number":4,"description":"Then SLIDER_HOME_PAGE should be an element that is visible","duration":126,"startTime":"2025-07-01T20:08:52.565237200-05:00[America/Bogota]","result":"SUCCESS","precondition":false,"level":1}]},{"number":5,"description":"When el usuario introduce un nombre \"Ana Isabel Patiño Osorio\" y un email \"anai.patino@udea.edu.co\" existente para registrarse","duration":2587,"startTime":"2025-07-01T20:08:52.699845800-05:00[America/Bogota]","result":"SUCCESS","precondition":false,"level":0,"children":[{"number":6,"description":"Usuario iniciar registro","duration":2546,"startTime":"2025-07-01T20:08:52.735828100-05:00[America/Bogota]","result":"SUCCESS","precondition":false,"level":1,"children":[{"number":7,"description":"Usuario clicks on SIGNUP_LOGIN_BUTTON","duration":904,"startTime":"2025-07-01T20:08:52.753422700-05:00[America/Bogota]","result":"SUCCESS","precondition":false,"level":2},{"number":8,"description":"Usuario enters \u0027Ana Isabel Patiño Osorio\u0027 into INPUT_NAME","duration":352,"startTime":"2025-07-01T20:08:53.689568600-05:00[America/Bogota]","result":"SUCCESS","precondition":false,"level":2},{"number":9,"description":"Usuario enters \u0027anai.patino@udea.edu.co\u0027 into INPUT_EMAIL","duration":276,"startTime":"2025-07-01T20:08:54.043760500-05:00[America/Bogota]","result":"SUCCESS","precondition":false,"level":2},{"number":10,"description":"Usuario clicks on SIGNUP_BUTTON","duration":954,"startTime":"2025-07-01T20:08:54.322033800-05:00[America/Bogota]","result":"SUCCESS","precondition":false,"level":2}]}]},{"number":11,"description":"Then aparece el mensaje Email Address already exist!","duration":93,"startTime":"2025-07-01T20:08:55.287338800-05:00[America/Bogota]","result":"SUCCESS","precondition":false,"level":0,"children":[{"number":12,"description":"Then contiene el texto should be (true)","duration":82,"startTime":"2025-07-01T20:08:55.287338800-05:00[America/Bogota]","result":"SUCCESS","precondition":false,"level":1}]}],"userStory":{"id":"registrar_usuario_existente","storyName":"Validación de registro con usuario existente","displayName":"Validación de registro con usuario existente","path":"registrar_usuario_existente","pathElements":[{"name":"registrar_usuario_existente","description":""}],"narrative":"  Como usuario de Automation Exercise\n  Quiero recibir una advertencia al intentar registrarme con un correo ya existente\n  Para evitar la creación duplicada de cuentas y proteger mis datos","type":"feature"},"title":"Registro de un usuario existente","description":"","tags":[{"name":"Chrome","type":"context","displayName":"Chrome"},{"name":"Windows","type":"context","displayName":"Windows"},{"name":"Chrome, Windows","type":"context","displayName":"Chrome, Windows"}],"startTime":"2025-07-01T20:08:46.450559300-05:00[America/Bogota]","duration":5963,"projectKey":"","sessionId":"e48d80d66ef9b26e944868b1b1cd2385","driver":"chrome:usuario","isManualTestingUpToDate":false,"context":"chrome,windows","manual":false,"testSource":"Cucumber","actors":[{"name":"Usuario","can":["browse the web"]}],"order":0,"result":"SUCCESS"}